python_docs_hook/__init__.py
python_docs_hook/main.py
python_docs_hook/tests/__init__.py
python_docs_hook/tests/test_main.py
python_docs_hook-0.1.13.dist-info/METADATA
python_docs_hook-0.1.13.dist-info/WHEEL
python_docs_hook-0.1.13.dist-info/entry_points.txt
python_docs_hook-0.1.13.dist-info/top_level.txt
python_docs_hook-0.1.13.dist-info/RECORD
