Metadata-Version: 2.2
Name: python_docs_hook
Version: 0.1.13
Summary: A pre-commit hook to generate Python documentation
Home-page: https://github.com/geek-kb/python_docs_hook
Author: Itai Ganot
Author-email: lel@lel.bz
Classifier: Programming Language :: Python :: 3
Classifier: License :: OSI Approved :: MIT License
Classifier: Operating System :: OS Independent
Requires-Python: >=3.6
Dynamic: author
Dynamic: author-email
Dynamic: classifier
Dynamic: description
Dynamic: description-content-type
Dynamic: home-page
Dynamic: requires-python
Dynamic: summary
